proxy.py
fogproxy-0.5.0.dist-info/DESCRIPTION.rst
fogproxy-0.5.0.dist-info/METADATA
fogproxy-0.5.0.dist-info/RECORD
fogproxy-0.5.0.dist-info/WHEEL
fogproxy-0.5.0.dist-info/entry_points.txt
fogproxy-0.5.0.dist-info/metadata.json
fogproxy-0.5.0.dist-info/top_level.txt
