Metadata-Version: 2.0
Name: fogproxy
Version: 0.5.0
Summary: FogBugz scout report proxy with attachment support
Home-page: https://gitlab.com/develer/fogproxy
Author: Matteo Bertini
Author-email: naufraghi@develer.com
License: MIT
Keywords: bugreport proxy fogbugz
Platform: UNKNOWN
Classifier: Intended Audience :: System Administrators
Classifier: Intended Audience :: Developers
Classifier: License :: OSI Approved :: MIT License
Classifier: Programming Language :: Python :: 3
Requires-Dist: bottle (>=0.13)
Requires-Dist: click (==6.3)
Requires-Dist: dirq (==1.7)
Requires-Dist: requests (==2.9.1)
